{
	"name": "CopyPipeline_iey",
	"properties": {
		"activities": [
			{
				"name": "SQL to Bob",
				"type": "Copy",
				"dependsOn": [
					{
						"activity": "Data avl",
						"dependencyConditions": [
							"Succeeded"
						]
					}
				],
				"policy": {
					"timeout": "7.00:00:00",
					"retry": 0,
					"retryIntervalInSeconds": 30,
					"secureOutput": false,
					"secureInput": false
				},
				"userProperties": [
					{
						"name": "Source",
						"value": "Purchasing.PurchaseOrders"
					},
					{
						"name": "Destination",
						"value": "badatabase-bacpc//"
					}
				],
				"typeProperties": {
					"source": {
						"type": "AzureSqlSource",
						"partitionOption": "None"
					},
					"sink": {
						"type": "DelimitedTextSink",
						"storeSettings": {
							"type": "AzureBlobStorageWriteSettings"
						},
						"formatSettings": {
							"type": "DelimitedTextWriteSettings",
							"quoteAllText": true,
							"fileExtension": ".txt"
						}
					},
					"enableStaging": false,
					"validateDataConsistency": false,
					"translator": {
						"type": "TabularTranslator",
						"mappings": [
							{
								"source": {
									"name": "PurchaseOrderID",
									"type": "Int32"
								},
								"sink": {
									"name": "PurchaseOrderID",
									"type": "String"
								}
							},
							{
								"source": {
									"name": "SupplierID",
									"type": "Int32"
								},
								"sink": {
									"name": "SupplierID",
									"type": "String"
								}
							},
							{
								"source": {
									"name": "OrderDate",
									"type": "DateTime"
								},
								"sink": {
									"name": "OrderDate",
									"type": "String"
								}
							},
							{
								"source": {
									"name": "DeliveryMethodID",
									"type": "Int32"
								},
								"sink": {
									"name": "DeliveryMethodID",
									"type": "String"
								}
							},
							{
								"source": {
									"name": "ContactPersonID",
									"type": "Int32"
								},
								"sink": {
									"name": "ContactPersonID",
									"type": "String"
								}
							},
							{
								"source": {
									"name": "ExpectedDeliveryDate",
									"type": "DateTime"
								},
								"sink": {
									"name": "ExpectedDeliveryDate",
									"type": "String"
								}
							},
							{
								"source": {
									"name": "SupplierReference",
									"type": "String"
								},
								"sink": {
									"name": "SupplierReference",
									"type": "String"
								}
							},
							{
								"source": {
									"name": "IsOrderFinalized",
									"type": "Boolean"
								},
								"sink": {
									"name": "IsOrderFinalized",
									"type": "String"
								}
							},
							{
								"source": {
									"name": "Comments",
									"type": "String"
								},
								"sink": {
									"name": "Comments",
									"type": "String"
								}
							},
							{
								"source": {
									"name": "InternalComments",
									"type": "String"
								},
								"sink": {
									"name": "InternalComments",
									"type": "String"
								}
							},
							{
								"source": {
									"name": "LastEditedBy",
									"type": "Int32"
								},
								"sink": {
									"name": "LastEditedBy",
									"type": "String"
								}
							},
							{
								"source": {
									"name": "LastEditedWhen",
									"type": "DateTime"
								},
								"sink": {
									"name": "LastEditedWhen",
									"type": "String"
								}
							}
						]
					}
				},
				"inputs": [
					{
						"referenceName": "SourceDataset_iey",
						"type": "DatasetReference"
					}
				],
				"outputs": [
					{
						"referenceName": "DestinationDataset_iey",
						"type": "DatasetReference"
					}
				]
			},
			{
				"name": "Get holding Updates",
				"type": "SqlServerStoredProcedure",
				"dependsOn": [
					{
						"activity": "SQL to Bob",
						"dependencyConditions": [
							"Succeeded"
						]
					}
				],
				"policy": {
					"timeout": "7.00:00:00",
					"retry": 0,
					"retryIntervalInSeconds": 30,
					"secureOutput": false,
					"secureInput": false
				},
				"userProperties": [],
				"typeProperties": {
					"storedProcedureName": "[Integration].[GetStockHoldingUpdates]"
				},
				"linkedServiceName": {
					"referenceName": "AzureSqlDatabase2",
					"type": "LinkedServiceReference"
				}
			},
			{
				"name": "data fail",
				"type": "WebActivity",
				"dependsOn": [
					{
						"activity": "SQL to Bob",
						"dependencyConditions": [
							"Failed"
						]
					}
				],
				"policy": {
					"timeout": "7.00:00:00",
					"retry": 0,
					"retryIntervalInSeconds": 30,
					"secureOutput": false,
					"secureInput": false
				},
				"userProperties": [],
				"typeProperties": {
					"url": "bvsreddy8888@gmail.com",
					"method": "GET"
				}
			},
			{
				"name": "Data avl",
				"type": "Lookup",
				"dependsOn": [],
				"policy": {
					"timeout": "7.00:00:00",
					"retry": 0,
					"retryIntervalInSeconds": 30,
					"secureOutput": false,
					"secureInput": false
				},
				"userProperties": [],
				"typeProperties": {
					"source": {
						"type": "AzureSqlSource",
						"queryTimeout": "02:00:00",
						"partitionOption": "None"
					},
					"dataset": {
						"referenceName": "SourceDataset_iey",
						"type": "DatasetReference"
					}
				}
			},
			{
				"name": "final data",
				"type": "Copy",
				"dependsOn": [
					{
						"activity": "Get holding Updates",
						"dependencyConditions": [
							"Succeeded"
						]
					}
				],
				"policy": {
					"timeout": "7.00:00:00",
					"retry": 0,
					"retryIntervalInSeconds": 30,
					"secureOutput": false,
					"secureInput": false
				},
				"userProperties": [],
				"typeProperties": {
					"source": {
						"type": "AzureSqlSource",
						"sqlReaderStoredProcedureName": "[Integration].[GetStockHoldingUpdates]",
						"queryTimeout": "02:00:00",
						"partitionOption": "None"
					},
					"sink": {
						"type": "DelimitedTextSink",
						"storeSettings": {
							"type": "AzureBlobStorageWriteSettings"
						},
						"formatSettings": {
							"type": "DelimitedTextWriteSettings",
							"quoteAllText": true,
							"fileExtension": ".csv"
						}
					},
					"enableStaging": false,
					"translator": {
						"type": "TabularTranslator",
						"mappings": [
							{
								"source": {
									"name": "Quantity On Hand",
									"type": "Int32",
									"physicalType": "int"
								},
								"sink": {
									"name": "Quantity On Hand",
									"type": "String",
									"physicalType": "String"
								}
							},
							{
								"source": {
									"name": "Bin Location",
									"type": "String",
									"physicalType": "nvarchar"
								},
								"sink": {
									"name": "Bin Location",
									"type": "String",
									"physicalType": "String"
								}
							},
							{
								"source": {
									"name": "Last Stocktake Quantity",
									"type": "Int32",
									"physicalType": "int"
								},
								"sink": {
									"name": "Last Stocktake Quantity",
									"type": "String",
									"physicalType": "String"
								}
							},
							{
								"source": {
									"name": "Last Cost Price",
									"type": "Decimal",
									"physicalType": "decimal",
									"scale": 2,
									"precision": 18
								},
								"sink": {
									"name": "Last Cost Price",
									"type": "String",
									"physicalType": "String"
								}
							},
							{
								"source": {
									"name": "Reorder Level",
									"type": "Int32",
									"physicalType": "int"
								},
								"sink": {
									"name": "Reorder Level",
									"type": "String",
									"physicalType": "String"
								}
							},
							{
								"source": {
									"name": "Target Stock Level",
									"type": "Int32",
									"physicalType": "int"
								},
								"sink": {
									"name": "Target Stock Level",
									"type": "String",
									"physicalType": "String"
								}
							},
							{
								"source": {
									"name": "WWI Stock Item ID",
									"type": "Int32",
									"physicalType": "int"
								},
								"sink": {
									"name": "WWI Stock Item ID",
									"type": "String",
									"physicalType": "String"
								}
							}
						],
						"typeConversion": true,
						"typeConversionSettings": {
							"allowDataTruncation": true,
							"treatBooleanAsNumber": false
						}
					}
				},
				"inputs": [
					{
						"referenceName": "SourceDataset_iey",
						"type": "DatasetReference"
					}
				],
				"outputs": [
					{
						"referenceName": "DestinationDataset_iey",
						"type": "DatasetReference"
					}
				]
			}
		],
		"annotations": [],
		"lastPublishTime": "2021-09-25T15:26:17Z"
	},
	"type": "Microsoft.DataFactory/factories/pipelines"
}